<?xml version="1.0" encoding="utf-8"?>
<demos><!--This is an autogenerated file, please do not modify-->
   <name>junit-xml-ml</name>
   <type>toolbox</type>
   <icon>HelpIcon.DEMOS</icon>
   <website/>
   <description>Creates JUnit XML test result documents that can be read by tools such as Jenkins. Aims to be the Matlab equivalent of junit-xml for Python.

A Matlab class for creating JUnit XML test result documents that can be read by tools such as Jenkins. If you are ever working with test tool or test suite written in Matlab and want to take advantage of Jenkins' graphs and test reporting capabilities, this module will let you generate the XML test reports.</description>
   <demosection>
      <label>Examples</label>
      <demoitem>
         <label>Example01</label>
         <type>other</type>
         <source>Example01</source>
         <file>Examples/html/Example01.html</file>
      </demoitem>
      <demoitem>
         <label>Example02</label>
         <type>other</type>
         <source>Example02</source>
         <file>Examples/html/Example02.html</file>
      </demoitem>
      <demoitem>
         <label>Example03</label>
         <type>other</type>
         <source>Example03</source>
         <file>Examples/html/Example03.html</file>
      </demoitem>
      <demoitem>
         <label>Example04</label>
         <type>other</type>
         <source>Example04</source>
         <file>Examples/html/Example04.html</file>
      </demoitem>
      <demoitem>
         <label>Example10</label>
         <type>other</type>
         <source>Example10</source>
         <file>Examples/html/Example10.html</file>
      </demoitem>
      <demoitem>
         <label>Example11</label>
         <type>other</type>
         <source>Example11</source>
         <file>Examples/html/Example11.html</file>
      </demoitem>
      <demoitem>
         <label>Example12</label>
         <type>other</type>
         <source>Example12</source>
         <file>Examples/html/Example12.html</file>
      </demoitem>
      <demoitem>
         <label>Example13</label>
         <type>other</type>
         <source>Example13</source>
         <file>Examples/html/Example13.html</file>
      </demoitem>
   </demosection>
</demos>